expa/__init__.py
expa/client.py
expa/logger.py
expa/db/__init__.py
expa/db/repository.py
expa/db/sql_store.py
expa/pubsub/__init__.py
expa/pubsub/client.py
expa/pubsub/pubsub.py
expa-0.2.0.dist-info/METADATA
expa-0.2.0.dist-info/WHEEL
expa-0.2.0.dist-info/top_level.txt
expa-0.2.0.dist-info/RECORD
