Metadata-Version: 2.1
Name: expa
Version: 0.2.0
Summary: Metric logging and analysis for ML experiments
Home-page: https://github.com/jurgisp/expa
Author: Jurgis Pasukonis
Author-email: jurgisp@gmail.com
License: Apache 2.0
Classifier: Intended Audience :: Science/Research
Classifier: License :: OSI Approved :: Apache Software License
Classifier: Programming Language :: Python :: 3
Classifier: Topic :: Scientific/Engineering :: Artificial Intelligence
Classifier: Topic :: Scientific/Engineering :: Visualization
Requires-Python: >=3.9
Requires-Dist: numpy
Requires-Dist: requests
Provides-Extra: api
Requires-Dist: absl-py ; extra == 'api'
Requires-Dist: fastapi ; extra == 'api'
Requires-Dist: uvicorn ; extra == 'api'
Requires-Dist: orjson ; extra == 'api'
Provides-Extra: db
Requires-Dist: pandas ; extra == 'db'
Requires-Dist: asyncpg ; extra == 'db'
Provides-Extra: pubsub
Requires-Dist: msgpack ; extra == 'pubsub'
Requires-Dist: google-cloud-pubsub ; extra == 'pubsub'
